{
  "author": null,
  "author_email": null,
  "contributor": "Digitalisation & Data",
  "createddate": "",
  "creator": "Western Power Distribution",
  "creator_user_id": "9ba97dd9-1ade-407f-a018-92481e27c39b",
  "dataclassification": "Shared",
  "expirationdate": "",
  "id": "419d7eed-e2b1-4596-9427-d76edf19fb6e",
  "identifier": "WMGTF",
  "isopen": false,
  "language": "EN",
  "license_id": "",
  "license_title": "",
  "maintainer": null,
  "maintainer_email": null,
  "metadata_created": "2021-07-29T10:47:01.113680",
  "metadata_modified": "2025-05-09T15:23:38.400305",
  "name": "super-grid-transformer-flows-west-midlands",
  "notes": "Import, Generation, Demand and Voltage values at half hourly granularity per transformer from 31st March 2022 to 31st March 2023.",
  "num_resources": 19,
  "num_tags": 3,
  "organization": {
    "id": "a65a370a-a123-4d90-bdb9-fb176c382e83",
    "name": "national_grid_electricity_distribution",
    "title": "National Grid Electricity Distribution",
    "type": "organization",
    "description": "## National Grid Electricity Distribution is the regional electricity distribution division of National Grid.\r\n\r\nFormerly known as Western Power Distribution, the UK\u2019s largest electricity distribution network serves nearly 8 million customers in the East and West Midlands, South West and Wales, delivering essential power to millions of homes and businesses across its regions.\r\n\r\nWith a distribution area of 550,000 square kilometres, it\u2019s 6,500 colleagues are committed to providing a safe, stable and reliable electricity supply and ensuring the highest quality of customer service.",
    "image_url": "https://connecteddata.nationalgrid.co.uk/base/images/logo.svg",
    "created": "2020-12-03T20:28:20.647977",
    "is_organization": true,
    "approval_status": "approved",
    "state": "active"
  },
  "owner_org": "a65a370a-a123-4d90-bdb9-fb176c382e83",
  "private": false,
  "publisher": "",
  "relation": "LTDS",
  "rights": "WPD Shared Data Licence",
  "state": "active",
  "title": "Super Grid Transformer Flows \u2013 West Midlands",
  "type": "dataset",
  "updatefrequency": "12 Months",
  "url": "",
  "version": null,
  "groups": [
    {
      "description": "This data group includes historic data and real time electricity demand",
      "display_name": "Demand",
      "id": "792bca32-651c-4f47-a394-7072a81cfc62",
      "image_display_url": "",
      "name": "demand",
      "title": "Demand"
    }
  ],
  "resources": [
    {
      "cache_last_updated": null,
      "cache_url": null,
      "created": "2022-07-22T09:28:58.523800",
      "datastore_active": true,
      "description": null,
      "format": "CSV",
      "hash": "",
      "id": "8f6c8c57-0e2a-45a0-becf-a1c21a9e37df",
      "last_modified": "2024-07-17T10:25:43.133689",
      "metadata_modified": "2024-07-17T10:25:43.194988",
      "mimetype": "text/csv",
      "mimetype_inner": null,
      "name": "Bishops Wood  BSPkV Transformer Flows",
      "outboundFile": "<starlette.datastructures.UploadFile object at 0x7fb79db19070>",
      "package_id": "419d7eed-e2b1-4596-9427-d76edf19fb6e",
      "position": 0,
      "resource_type": null,
      "restricted_level": "registered",
      "size": 22553136,
      "state": "active",
      "tracking_summary": {
        "total": 0,
        "recent": 0
      },
      "url": "redacted",
      "url_type": "upload",
      "wpd_datastore_last_updated": "EXTRA-2025-04-08T14:53:58.690290",
      "restricted": "redacted"
    },
    {
      "cache_last_updated": null,
      "cache_url": null,
      "created": "2022-07-22T09:29:40.581483",
      "datastore_active": true,
      "description": null,
      "format": "CSV",
      "hash": "",
      "id": "2aac4e57-a10a-4104-93b0-acb8f1e01ebe",
      "last_modified": "2024-07-17T10:26:27.328318",
      "metadata_modified": "2024-07-17T10:26:27.404316",
      "mimetype": "text/csv",
      "mimetype_inner": null,
      "name": "Bushbury  BSPkV Transformer Flows",
      "outboundFile": "<starlette.datastructures.UploadFile object at 0x7fb79db66100>",
      "package_id": "419d7eed-e2b1-4596-9427-d76edf19fb6e",
      "position": 1,
      "resource_type": null,
      "restricted_level": "registered",
      "size": 16817113,
      "state": "active",
      "tracking_summary": {
        "total": 0,
        "recent": 0
      },
      "url": "redacted",
      "url_type": "upload",
      "wpd_datastore_last_updated": "EXTRA-2025-04-08T14:56:34.829655",
      "restricted": "redacted"
    },
    {
      "cache_last_updated": null,
      "cache_url": null,
      "created": "2022-07-22T09:30:20.351953",
      "datastore_active": true,
      "description": null,
      "format": "CSV",
      "hash": "",
      "id": "64044d1d-ddf5-4657-9fdb-51843b84fb98",
      "last_modified": "2024-07-17T10:27:32.170836",
      "metadata_modified": "2024-07-17T10:27:32.242433",
      "mimetype": "text/csv",
      "mimetype_inner": null,
      "name": "Bustleholm  BSPkV Transformer Flows",
      "outboundFile": "<starlette.datastructures.UploadFile object at 0x7fb79d984c40>",
      "package_id": "419d7eed-e2b1-4596-9427-d76edf19fb6e",
      "position": 2,
      "resource_type": null,
      "restricted_level": "registered",
      "size": 23018137,
      "state": "active",
      "tracking_summary": {
        "total": 0,
        "recent": 0
      },
      "url": "redacted",
      "url_type": "upload",
      "wpd_datastore_last_updated": "EXTRA-2025-04-08T15:04:36.699607",
      "restricted": "redacted"
    },
    {
      "cache_last_updated": null,
      "cache_url": null,
      "created": "2022-07-22T09:31:31.260356",
      "datastore_active": true,
      "description": null,
      "format": "CSV",
      "hash": "",
      "id": "4edc9eb7-b6f8-499a-8f1c-1ca6cd0215df",
      "last_modified": "2024-07-17T10:27:50.273648",
      "metadata_modified": "2024-07-17T10:27:50.364404",
      "mimetype": "text/csv",
      "mimetype_inner": null,
      "name": "East Claydon  BSPkV Transformer Flows",
      "outboundFile": "<starlette.datastructures.UploadFile object at 0x7fb79da78a00>",
      "package_id": "419d7eed-e2b1-4596-9427-d76edf19fb6e",
      "position": 3,
      "resource_type": null,
      "restricted_level": "registered",
      "size": 5849328,
      "state": "active",
      "tracking_summary": {
        "total": 0,
        "recent": 0
      },
      "url": "redacted",
      "url_type": "upload",
      "wpd_datastore_last_updated": "EXTRA-2025-04-08T14:59:58.506129",
      "restricted": "redacted"
    },
    {
      "cache_last_updated": null,
      "cache_url": null,
      "created": "2022-07-22T09:32:21.095136",
      "datastore_active": true,
      "description": null,
      "format": "CSV",
      "hash": "",
      "id": "2dc2044c-04d8-459f-9c65-3457ac0ee588",
      "last_modified": "2024-07-17T10:28:41.775957",
      "metadata_modified": "2024-07-17T10:28:41.859036",
      "mimetype": "text/csv",
      "mimetype_inner": null,
      "name": "Feckenham  BSPkV Transformer Flows",
      "outboundFile": "<starlette.datastructures.UploadFile object at 0x7fb79da78520>",
      "package_id": "419d7eed-e2b1-4596-9427-d76edf19fb6e",
      "position": 4,
      "resource_type": null,
      "restricted_level": "registered",
      "size": 20163273,
      "state": "active",
      "tracking_summary": {
        "total": 0,
        "recent": 0
      },
      "url": "redacted",
      "url_type": "upload",
      "wpd_datastore_last_updated": "EXTRA-2025-04-08T15:14:41.045120",
      "restricted": "redacted"
    },
    {
      "cache_last_updated": null,
      "cache_url": null,
      "created": "2022-07-22T09:33:20.028838",
      "datastore_active": true,
      "description": null,
      "format": "CSV",
      "hash": "",
      "id": "40d2fcf3-0030-47e5-948d-73577631ba19",
      "last_modified": "2024-07-17T10:30:09.761517",
      "metadata_modified": "2024-07-17T10:30:09.848828",
      "mimetype": "text/csv",
      "mimetype_inner": null,
      "name": "Iron Acton  BSPkV Transformer Flows",
      "outboundFile": "<starlette.datastructures.UploadFile object at 0x7fb79d9af5e0>",
      "package_id": "419d7eed-e2b1-4596-9427-d76edf19fb6e",
      "position": 5,
      "resource_type": null,
      "restricted_level": "registered",
      "size": 33564133,
      "state": "active",
      "tracking_summary": {
        "total": 0,
        "recent": 0
      },
      "url": "redacted",
      "url_type": "upload",
      "wpd_datastore_last_updated": "EXTRA-2025-04-08T15:28:48.876848",
      "restricted": "redacted"
    },
    {
      "cache_last_updated": null,
      "cache_url": null,
      "created": "2022-07-22T09:33:49.875712",
      "datastore_active": true,
      "description": null,
      "format": "CSV",
      "hash": "",
      "id": "80cb45a7-251d-4445-b982-0204d3ddc057",
      "last_modified": "2024-07-17T10:30:53.524790",
      "metadata_modified": "2024-07-17T10:30:53.581944",
      "mimetype": "text/csv",
      "mimetype_inner": null,
      "name": "Ironbridge  BSPkV Transformer Flows",
      "outboundFile": "<starlette.datastructures.UploadFile object at 0x7fb79d368790>",
      "package_id": "419d7eed-e2b1-4596-9427-d76edf19fb6e",
      "position": 6,
      "resource_type": null,
      "restricted_level": "registered",
      "size": 15239187,
      "state": "active",
      "tracking_summary": {
        "total": 0,
        "recent": 0
      },
      "url": "redacted",
      "url_type": "upload",
      "wpd_datastore_last_updated": "EXTRA-2025-04-08T15:22:12.826614",
      "restricted": "redacted"
    },
    {
      "cache_last_updated": null,
      "cache_url": null,
      "created": "2022-07-22T09:34:39.035427",
      "datastore_active": true,
      "description": null,
      "format": "CSV",
      "hash": "",
      "id": "3c3cc4d2-cb00-4a05-9f82-18ff74534220",
      "last_modified": "2024-07-17T10:31:49.567603",
      "metadata_modified": "2024-07-17T10:31:49.623187",
      "mimetype": "text/csv",
      "mimetype_inner": null,
      "name": "Kitwell  BSPkV Transformer Flows",
      "outboundFile": "<starlette.datastructures.UploadFile object at 0x7fb79db7ed00>",
      "package_id": "419d7eed-e2b1-4596-9427-d76edf19fb6e",
      "position": 7,
      "resource_type": null,
      "restricted_level": "registered",
      "size": 22306589,
      "state": "active",
      "tracking_summary": {
        "total": 0,
        "recent": 0
      },
      "url": "redacted",
      "url_type": "upload",
      "wpd_datastore_last_updated": "EXTRA-2025-04-08T15:32:27.254119",
      "restricted": "redacted"
    },
    {
      "cache_last_updated": null,
      "cache_url": null,
      "created": "2022-07-22T09:35:24.708726",
      "datastore_active": true,
      "description": null,
      "format": "CSV",
      "hash": "",
      "id": "c3bb6c24-fdb4-4c56-ae2e-e2bd3427b07b",
      "last_modified": "2024-07-17T10:32:46.378335",
      "metadata_modified": "2024-07-17T10:32:46.437119",
      "mimetype": "text/csv",
      "mimetype_inner": null,
      "name": "Lea Marston  BSPkV Transformer Flows",
      "outboundFile": "<starlette.datastructures.UploadFile object at 0x7fb79daa6e50>",
      "package_id": "419d7eed-e2b1-4596-9427-d76edf19fb6e",
      "position": 8,
      "resource_type": null,
      "restricted_level": "registered",
      "size": 21355084,
      "state": "active",
      "tracking_summary": {
        "total": 0,
        "recent": 0
      },
      "url": "redacted",
      "url_type": "upload",
      "wpd_datastore_last_updated": "EXTRA-2025-04-08T15:36:46.537842",
      "restricted": "redacted"
    },
    {
      "cache_last_updated": null,
      "cache_url": null,
      "created": "2022-07-22T09:36:09.422910",
      "datastore_active": true,
      "description": null,
      "format": "CSV",
      "hash": "",
      "id": "fad06e58-8681-4356-ab8e-1b9eaf1a9488",
      "last_modified": "2024-07-17T10:33:35.972497",
      "metadata_modified": "2024-07-17T10:33:36.041876",
      "mimetype": "text/csv",
      "mimetype_inner": null,
      "name": "Nechells  BSPkV Transformer Flows",
      "outboundFile": "<starlette.datastructures.UploadFile object at 0x7fb79da42640>",
      "package_id": "419d7eed-e2b1-4596-9427-d76edf19fb6e",
      "position": 9,
      "resource_type": null,
      "restricted_level": "registered",
      "size": 20154037,
      "state": "active",
      "tracking_summary": {
        "total": 0,
        "recent": 0
      },
      "url": "redacted",
      "url_type": "upload",
      "wpd_datastore_last_updated": "EXTRA-2025-04-08T15:41:15.951764",
      "restricted": "redacted"
    },
    {
      "cache_last_updated": null,
      "cache_url": null,
      "created": "2022-07-22T09:36:46.558353",
      "datastore_active": true,
      "description": null,
      "format": "CSV",
      "hash": "",
      "id": "99eca4bd-61b3-4e54-a42c-004f39aa40d8",
      "last_modified": "2024-07-17T10:34:18.468479",
      "metadata_modified": "2024-07-17T10:34:18.523020",
      "mimetype": "text/csv",
      "mimetype_inner": null,
      "name": "Ocker Hill  BSPkV Transformer Flows",
      "outboundFile": "<starlette.datastructures.UploadFile object at 0x7fb79d6e6940>",
      "package_id": "419d7eed-e2b1-4596-9427-d76edf19fb6e",
      "position": 10,
      "resource_type": null,
      "restricted_level": "registered",
      "size": 16817171,
      "state": "active",
      "tracking_summary": {
        "total": 0,
        "recent": 0
      },
      "url": "redacted",
      "url_type": "upload",
      "wpd_datastore_last_updated": "EXTRA-2025-04-08T15:42:42.987676",
      "restricted": "redacted"
    },
    {
      "cache_last_updated": null,
      "cache_url": null,
      "created": "2022-07-22T09:37:18.886725",
      "datastore_active": true,
      "description": null,
      "format": "CSV",
      "hash": "",
      "id": "2e70c14d-c31a-4b9e-919b-83bc88cf3822",
      "last_modified": "2024-07-17T10:34:39.998331",
      "metadata_modified": "2024-07-17T10:34:40.057866",
      "mimetype": "text/csv",
      "mimetype_inner": null,
      "name": "Oldbury  BSPkV Transformer Flows",
      "outboundFile": "<starlette.datastructures.UploadFile object at 0x7fb79d6de760>",
      "package_id": "419d7eed-e2b1-4596-9427-d76edf19fb6e",
      "position": 11,
      "resource_type": null,
      "restricted_level": "registered",
      "size": 8068414,
      "state": "active",
      "tracking_summary": {
        "total": 0,
        "recent": 0
      },
      "url": "redacted",
      "url_type": "upload",
      "wpd_datastore_last_updated": "EXTRA-2025-04-08T15:42:12.274777",
      "restricted": "redacted"
    },
    {
      "cache_last_updated": null,
      "cache_url": null,
      "created": "2022-07-22T09:37:58.352176",
      "datastore_active": true,
      "description": null,
      "format": "CSV",
      "hash": "",
      "id": "7c04566d-16a9-4dab-9be8-926f368f380a",
      "last_modified": "2024-07-17T10:35:17.092788",
      "metadata_modified": "2024-07-17T10:35:17.161389",
      "mimetype": "text/csv",
      "mimetype_inner": null,
      "name": "Penn  BSPkV Transformer Flows",
      "outboundFile": "<starlette.datastructures.UploadFile object at 0x7fb79d966790>",
      "package_id": "419d7eed-e2b1-4596-9427-d76edf19fb6e",
      "position": 12,
      "resource_type": null,
      "restricted_level": "registered",
      "size": 15420608,
      "state": "active",
      "tracking_summary": {
        "total": 0,
        "recent": 0
      },
      "url": "redacted",
      "url_type": "upload",
      "wpd_datastore_last_updated": "EXTRA-2025-04-08T15:51:00.160491",
      "restricted": "redacted"
    },
    {
      "cache_last_updated": null,
      "cache_url": null,
      "created": "2022-07-22T09:38:45.605304",
      "datastore_active": true,
      "description": null,
      "format": "CSV",
      "hash": "",
      "id": "40ce56d6-201b-4303-ab68-6168e4414918",
      "last_modified": "2024-07-17T10:36:09.178154",
      "metadata_modified": "2024-07-17T10:36:09.235977",
      "mimetype": "text/csv",
      "mimetype_inner": null,
      "name": "Port Ham  BSPkV Transformer Flows",
      "outboundFile": "<starlette.datastructures.UploadFile object at 0x7fb79da60c10>",
      "package_id": "419d7eed-e2b1-4596-9427-d76edf19fb6e",
      "position": 13,
      "resource_type": null,
      "restricted_level": "registered",
      "size": 22010831,
      "state": "active",
      "tracking_summary": {
        "total": 0,
        "recent": 0
      },
      "url": "redacted",
      "url_type": "upload",
      "wpd_datastore_last_updated": "EXTRA-2025-04-08T15:59:30.451944",
      "restricted": "redacted"
    },
    {
      "cache_last_updated": null,
      "cache_url": null,
      "created": "2022-07-22T09:39:19.858425",
      "datastore_active": true,
      "description": null,
      "format": "CSV",
      "hash": "",
      "id": "4991a788-4b4d-4a51-b1b5-682de8258dc5",
      "last_modified": "2024-07-17T10:36:36.966240",
      "metadata_modified": "2024-07-17T10:36:37.023353",
      "mimetype": "text/csv",
      "mimetype_inner": null,
      "name": "Rugeley  BSPkV Transformer Flows",
      "outboundFile": "<starlette.datastructures.UploadFile object at 0x7fb79d6d3970>",
      "package_id": "419d7eed-e2b1-4596-9427-d76edf19fb6e",
      "position": 14,
      "resource_type": null,
      "restricted_level": "registered",
      "size": 10697073,
      "state": "active",
      "tracking_summary": {
        "total": 0,
        "recent": 0
      },
      "url": "redacted",
      "url_type": "upload",
      "wpd_datastore_last_updated": "EXTRA-2025-04-08T15:58:27.197137",
      "restricted": "redacted"
    },
    {
      "cache_last_updated": null,
      "cache_url": null,
      "created": "2022-07-22T09:39:47.436140",
      "datastore_active": true,
      "description": null,
      "format": "CSV",
      "hash": "",
      "id": "7d4bedcc-6500-41bc-b36e-aca779e3017c",
      "last_modified": "2024-07-17T10:36:49.875609",
      "metadata_modified": "2024-07-17T10:36:49.943599",
      "mimetype": "text/csv",
      "mimetype_inner": null,
      "name": "Shrewsbury  BSPkV Transformer Flows",
      "outboundFile": "<starlette.datastructures.UploadFile object at 0x7fb79db1a880>",
      "package_id": "419d7eed-e2b1-4596-9427-d76edf19fb6e",
      "position": 15,
      "resource_type": null,
      "restricted_level": "registered",
      "size": 4084323,
      "state": "active",
      "tracking_summary": {
        "total": 0,
        "recent": 0
      },
      "url": "redacted",
      "url_type": "upload",
      "wpd_datastore_last_updated": "EXTRA-2025-04-08T15:59:29.705164",
      "restricted": "redacted"
    },
    {
      "cache_last_updated": null,
      "cache_url": null,
      "created": "2022-07-22T09:40:25.392315",
      "datastore_active": true,
      "description": null,
      "format": "CSV",
      "hash": "",
      "id": "78a66572-96f1-41c6-b751-c71ff44e8a85",
      "last_modified": "2024-07-17T10:37:17.021226",
      "metadata_modified": "2024-07-17T10:37:17.082038",
      "mimetype": "text/csv",
      "mimetype_inner": null,
      "name": "Willenhall  BSPkV Transformer Flows",
      "outboundFile": "<starlette.datastructures.UploadFile object at 0x7fb79d6d3c70>",
      "package_id": "419d7eed-e2b1-4596-9427-d76edf19fb6e",
      "position": 16,
      "resource_type": null,
      "restricted_level": "registered",
      "size": 11260693,
      "state": "active",
      "tracking_summary": {
        "total": 0,
        "recent": 0
      },
      "url": "redacted",
      "url_type": "upload",
      "wpd_datastore_last_updated": "EXTRA-2025-04-08T16:08:10.843385",
      "restricted": "redacted"
    },
    {
      "cache_last_updated": null,
      "cache_url": null,
      "created": "2024-06-05T19:29:02.882831",
      "datastore_active": false,
      "description": "",
      "format": "PDF",
      "hash": "",
      "id": "c5ad8723-7b0b-47c7-a65e-7e927a537dab",
      "last_modified": "2024-06-05T19:29:02.807169",
      "metadata_modified": "2024-06-08T14:58:22.122355",
      "mimetype": "application/pdf",
      "mimetype_inner": null,
      "name": "Data Sharing Assessment",
      "package_id": "419d7eed-e2b1-4596-9427-d76edf19fb6e",
      "position": 17,
      "resource_type": null,
      "restricted_level": "public",
      "size": 123169,
      "state": "active",
      "tracking_summary": {
        "total": 0,
        "recent": 0
      },
      "url": "https://connecteddata.nationalgrid.co.uk/dataset/419d7eed-e2b1-4596-9427-d76edf19fb6e/resource/c5ad8723-7b0b-47c7-a65e-7e927a537dab/download/dsa086-super-grid-transformer-flows-west-midlands.pdf",
      "url_type": "upload"
    },
    {
      "cache_last_updated": null,
      "cache_url": null,
      "created": "2025-05-09T15:07:41.805437",
      "datastore_active": true,
      "description": "",
      "format": "CSV",
      "hash": "",
      "id": "bbac237d-b933-4217-8218-a2f01b9196cb",
      "last_modified": "2025-05-09T15:07:41.672105",
      "metadata_modified": "2025-05-09T15:08:34.103655",
      "mimetype": "text/csv",
      "mimetype_inner": null,
      "name": "Cellarhead BSPkV Transformer Flows",
      "package_id": "419d7eed-e2b1-4596-9427-d76edf19fb6e",
      "position": 18,
      "resource_type": null,
      "restricted_allowed_users": "",
      "restricted_level": "public",
      "size": 28242386,
      "state": "active",
      "tracking_summary": {
        "total": 0,
        "recent": 0
      },
      "url": "https://connecteddata.nationalgrid.co.uk/dataset/419d7eed-e2b1-4596-9427-d76edf19fb6e/resource/bbac237d-b933-4217-8218-a2f01b9196cb/download/cellarhead-132kv.csv",
      "url_type": "upload",
      "wpd_datastore_last_updated": "EXTRA-2025-05-09T15:23:38.400305"
    }
  ],
  "tags": [
    {
      "display_name": "Demand",
      "id": "3d75a4b3-83ea-4233-83b8-8c7d8b85a780",
      "name": "Demand",
      "state": "active",
      "vocabulary_id": null
    },
    {
      "display_name": "Generation",
      "id": "cf9c57c8-7779-4c2d-b0c1-dfc5def15e76",
      "name": "Generation",
      "state": "active",
      "vocabulary_id": null
    },
    {
      "display_name": "Import",
      "id": "b9b03371-d863-43d7-9f88-1d1751f4985c",
      "name": "Import",
      "state": "active",
      "vocabulary_id": null
    }
  ],
  "relationships_as_subject": [],
  "relationships_as_object": []
}